pymassspec_plot/__init__.py
pymassspec_plot/utils.py
pymassspec_plot-0.2.1.dist-info/LICENSE
pymassspec_plot-0.2.1.dist-info/METADATA
pymassspec_plot-0.2.1.dist-info/WHEEL
pymassspec_plot-0.2.1.dist-info/entry_points.txt
pymassspec_plot-0.2.1.dist-info/RECORD
