Metadata-Version: 2.2
Name: pymassspec-plot
Version: 0.2.1
Summary: Plotting extension for PyMassSpec.
Author-email: Dominic Davis-Foster <dominic@davis-foster.co.uk>
License: GPL-2.0-only
Keywords: chemistry,chromatography,mass-spectrometry,visualization
Home-page: https://github.com/PyMassSpec/PyMassSpec-Plot
Project-URL: Issue Tracker, https://github.com/PyMassSpec/PyMassSpec-Plot/issues
Project-URL: Source Code, https://github.com/PyMassSpec/PyMassSpec-Plot
Project-URL: Documentation, https://pymassspec-plot.readthedocs.io/en/latest
Platform: Windows
Platform: macOS
Platform: Linux
Classifier: Development Status :: 5 - Production/Stable
Classifier: Framework :: Matplotlib
Classifier: Intended Audience :: Developers
Classifier: Intended Audience :: Education
Classifier: Intended Audience :: End Users/Desktop
Classifier: Intended Audience :: Science/Research
Classifier: License :: OSI Approved :: GNU General Public License v2 (GPLv2)
Classifier: Operating System :: OS Independent
Classifier: Programming Language :: Python
Classifier: Programming Language :: Python :: 3 :: Only
Classifier: Programming Language :: Python :: 3.7
Classifier: Programming Language :: Python :: 3.8
Classifier: Programming Language :: Python :: 3.9
Classifier: Programming Language :: Python :: 3.10
Classifier: Programming Language :: Python :: 3.11
Classifier: Programming Language :: Python :: 3.12
Classifier: Programming Language :: Python :: 3.13
Classifier: Programming Language :: Python :: Implementation :: CPython
Classifier: Topic :: Education
Classifier: Topic :: Scientific/Engineering :: Bio-Informatics
Classifier: Topic :: Scientific/Engineering :: Chemistry
Classifier: Topic :: Scientific/Engineering :: Visualization
Classifier: Topic :: Software Development :: Libraries :: Python Modules
Requires-Python: >=3.7
Requires-Dist: matplotlib>=3.2.2
Requires-Dist: pymassspec>=2.3.0
